clip_cpp/__init__.py
clip_cpp/clip.py
clip_cpp/exceptions.py
clip_cpp/file_download.py
clip_cpp/libclip.so
clip_cpp/libggml.so
clip_cpp-0.5.0.dist-info/METADATA
clip_cpp-0.5.0.dist-info/WHEEL
clip_cpp-0.5.0.dist-info/entry_points.txt
clip_cpp-0.5.0.dist-info/RECORD
