Metadata-Version: 2.1
Name: clip_cpp
Version: 0.5.0
Summary: CLIP inference with no big dependencies such as PyTorch, TensorFlow, Numpy or ONNX
Home-page: https://github.com/monatis
Keywords: ggml,clip,clip.cpp,image embeddings,image search
Author: Yusuf Sarıgöz
Author-email: yusufsarigoz@gmail.com
Requires-Python: >=3.8
Classifier: License :: OSI Approved :: MIT License
Classifier: Operating System :: POSIX :: Linux
Classifier: Programming Language :: Python :: 3
Classifier: Programming Language :: Python :: 3.8
Classifier: Programming Language :: Python :: 3.9
Classifier: Programming Language :: Python :: 3.10
Classifier: Programming Language :: Python :: 3.11
Project-URL: Repository, https://github.com/monatis/clip.cpp
